{
  "schema_version": 1,
  "kind": "bot",
  "id": "B0B8NPABH7X",
  "source": "slack",
  "first_seen_at": "2026-06-06T23:20:31.719025+00:00",
  "last_seen_at": "2026-06-07T19:37:26.834624+00:00",
  "consent": {
    "share_personal_knowledge_to_org": false
  },
  "shared_knowledge": [],
  "observed_in_spaces": {
    "slack:T0B8VMZS49J:C0B8R5ZJPKQ": {
      "count": 2083,
      "first_seen_at": "2026-06-06T23:20:31.719046+00:00",
      "last_seen_at": "2026-06-07T00:20:38.447939+00:00"
    },
    "slack:T0B8VMZS49J:C0B8R9N140N": {
      "count": 3621,
      "first_seen_at": "2026-06-07T00:31:48.157312+00:00",
      "last_seen_at": "2026-06-07T01:48:27.358726+00:00"
    },
    "slack:T0B8VMZS49J:C0B8Q53UKL5": {
      "count": 325,
      "first_seen_at": "2026-06-07T01:46:52.257661+00:00",
      "last_seen_at": "2026-06-07T02:08:01.011016+00:00"
    },
    "slack:T0B8VMZS49J:C0B8TG78JNA": {
      "count": 1623,
      "first_seen_at": "2026-06-07T16:52:43.086005+00:00",
      "last_seen_at": "2026-06-07T19:37:26.834643+00:00"
    }
  }
}